{"page": 6, "image": "p0006.png", "width": 1870, "height": 2560, "words": [{"text": "+", "x": 150, "y": 254, "w": 12, "h": 13, "conf": 46.0, "block": 1, "par": 1, "line": 1, "i": 0}, {"text": "Des", "x": 180, "y": 247, "w": 52, "h": 27, "conf": 96.0, "block": 1, "par": 1, "line": 1, "i": 1}, {"text": "activités", "x": 243, "y": 246, "w": 123, "h": 28, "conf": 93.0, "block": 1, "par": 1, "line": 1, "i": 2}, {"text": "communicatives", "x": 378, "y": 247, "w": 242, "h": 27, "conf": 92.0, "block": 1, "par": 1, "line": 1, "i": 3}, {"text": "permettent,", "x": 633, "y": 247, "w": 170, "h": 36, "conf": 95.0, "block": 1, "par": 1, "line": 1, "i": 4}, {"text": "en", "x": 815, "y": 254, "w": 35, "h": 20, "conf": 97.0, "block": 1, "par": 1, "line": 1, "i": 5}, {"text": "fin", "x": 862, "y": 244, "w": 36, "h": 29, "conf": 96.0, "block": 1, "par": 1, "line": 1, "i": 6}, {"text": "d'ouvrage,", "x": 910, "y": 245, "w": 156, "h": 37, "conf": 96.0, "block": 1, "par": 1, "line": 1, "i": 7}, {"text": "de", "x": 1079, "y": 245, "w": 35, "h": 29, "conf": 97.0, "block": 1, "par": 1, "line": 1, "i": 8}, {"text": "travailler", "x": 1125, "y": 245, "w": 127, "h": 29, "conf": 91.0, "block": 1, "par": 1, "line": 1, "i": 9}, {"text": "la", "x": 1263, "y": 245, "w": 22, "h": 29, "conf": 95.0, "block": 1, "par": 1, "line": 1, "i": 10}, {"text": "compréhension", "x": 1296, "y": 245, "w": 225, "h": 38, "conf": 96.0, "block": 1, "par": 1, "line": 1, "i": 11}, {"text": "et", "x": 1533, "y": 247, "w": 28, "h": 27, "conf": 96.0, "block": 1, "par": 1, "line": 1, "i": 12}, {"text": "la", "x": 1573, "y": 245, "w": 22, "h": 29, "conf": 93.0, "block": 1, "par": 1, "line": 1, "i": 13}, {"text": "produc-", "x": 1607, "y": 245, "w": 113, "h": 38, "conf": 92.0, "block": 1, "par": 1, "line": 1, "i": 14}, {"text": "tion", "x": 148, "y": 290, "w": 55, "h": 27, "conf": 96.0, "block": 1, "par": 1, "line": 2, "i": 15}, {"text": "orale", "x": 215, "y": 288, "w": 72, "h": 29, "conf": 96.0, "block": 1, "par": 1, "line": 2, "i": 16}, {"text": "et", "x": 299, "y": 290, "w": 28, "h": 27, "conf": 96.0, "block": 1, "par": 1, "line": 2, "i": 17}, {"text": "écrite", "x": 337, "y": 290, "w": 80, "h": 27, "conf": 96.0, "block": 1, "par": 1, "line": 2, "i": 18}, {"text": "en", "x": 428, "y": 296, "w": 34, "h": 21, "conf": 96.0, "block": 1, "par": 1, "line": 2, "i": 19}, {"text": "classe", "x": 474, "y": 288, "w": 83, "h": 29, "conf": 96.0, "block": 1, "par": 1, "line": 2, "i": 20}, {"text": "ou", "x": 569, "y": 296, "w": 35, "h": 21, "conf": 96.0, "block": 1, "par": 1, "line": 2, "i": 21}, {"text": "en", "x": 617, "y": 296, "w": 33, "h": 21, "conf": 93.0, "block": 1, "par": 1, "line": 2, "i": 22}, {"text": "auto-apprentissage.", "x": 663, "y": 290, "w": 291, "h": 36, "conf": 91.0, "block": 1, "par": 1, "line": 2, "i": 23}, {"text": "Elles", "x": 969, "y": 288, "w": 61, "h": 29, "conf": 95.0, "block": 1, "par": 1, "line": 2, "i": 24}, {"text": "se", "x": 1041, "y": 297, "w": 29, "h": 20, "conf": 95.0, "block": 1, "par": 1, "line": 2, "i": 25}, {"text": "composent", "x": 1081, "y": 290, "w": 164, "h": 35, "conf": 96.0, "block": 1, "par": 1, "line": 2, "i": 26}, {"text": "de", "x": 1255, "y": 288, "w": 35, "h": 29, "conf": 96.0, "block": 1, "par": 1, "line": 2, "i": 27}, {"text": "textes", "x": 1301, "y": 291, "w": 87, "h": 26, "conf": 96.0, "block": 1, "par": 1, "line": 2, "i": 28}, {"text": "ou", "x": 1399, "y": 297, "w": 36, "h": 20, "conf": 96.0, "block": 1, "par": 1, "line": 2, "i": 29}, {"text": "de", "x": 1447, "y": 288, "w": 35, "h": 29, "conf": 96.0, "block": 1, "par": 1, "line": 2, "i": 30}, {"text": "dialogues", "x": 1493, "y": 288, "w": 140, "h": 37, "conf": 93.0, "block": 1, "par": 1, "line": 2, "i": 31}, {"text": "enre-", "x": 1644, "y": 296, "w": 76, "h": 21, "conf": 91.0, "block": 1, "par": 1, "line": 2, "i": 32}, {"text": "gistrés", "x": 149, "y": 333, "w": 93, "h": 36, "conf": 93.0, "block": 1, "par": 1, "line": 3, "i": 33}, {"text": "et", "x": 253, "y": 334, "w": 29, "h": 27, "conf": 93.0, "block": 1, "par": 1, "line": 3, "i": 34}, {"text": "retranscrits", "x": 295, "y": 334, "w": 159, "h": 27, "conf": 92.0, "block": 1, "par": 1, "line": 3, "i": 35}, {"text": "accompagnés", "x": 467, "y": 333, "w": 201, "h": 36, "conf": 96.0, "block": 1, "par": 1, "line": 3, "i": 36}, {"text": "de", "x": 681, "y": 331, "w": 35, "h": 30, "conf": 96.0, "block": 1, "par": 1, "line": 3, "i": 37}, {"text": "questions,", "x": 729, "y": 334, "w": 147, "h": 35, "conf": 96.0, "block": 1, "par": 1, "line": 3, "i": 38}, {"text": "d'exercices", "x": 891, "y": 331, "w": 160, "h": 30, "conf": 95.0, "block": 1, "par": 1, "line": 3, "i": 39}, {"text": "de", "x": 1063, "y": 331, "w": 36, "h": 30, "conf": 93.0, "block": 1, "par": 1, "line": 3, "i": 40}, {"text": "réemploi", "x": 1113, "y": 331, "w": 125, "h": 38, "conf": 91.0, "block": 1, "par": 1, "line": 3, "i": 41}, {"text": "ou", "x": 1252, "y": 340, "w": 36, "h": 21, "conf": 92.0, "block": 1, "par": 1, "line": 3, "i": 42}, {"text": "de", "x": 1302, "y": 331, "w": 35, "h": 30, "conf": 97.0, "block": 1, "par": 1, "line": 3, "i": 43}, {"text": "productions", "x": 1351, "y": 331, "w": 173, "h": 38, "conf": 96.0, "block": 1, "par": 1, "line": 3, "i": 44}, {"text": "à", "x": 1537, "y": 333, "w": 16, "h": 28, "conf": 96.0, "block": 1, "par": 1, "line": 3, "i": 45}, {"text": "partir", "x": 1567, "y": 334, "w": 77, "h": 35, "conf": 96.0, "block": 1, "par": 1, "line": 3, "i": 46}, {"text": "d'un", "x": 1655, "y": 331, "w": 65, "h": 30, "conf": 95.0, "block": 1, "par": 1, "line": 3, "i": 47}, {"text": "modèle.", "x": 149, "y": 375, "w": 115, "h": 30, "conf": 96.0, "block": 1, "par": 1, "line": 4, "i": 48}, {"text": "Ces", "x": 280, "y": 377, "w": 52, "h": 28, "conf": 95.0, "block": 1, "par": 1, "line": 4, "i": 49}, {"text": "documents", "x": 346, "y": 375, "w": 162, "h": 30, "conf": 95.0, "block": 1, "par": 1, "line": 4, "i": 50}, {"text": "renvoient", "x": 523, "y": 378, "w": 139, "h": 27, "conf": 96.0, "block": 1, "par": 1, "line": 4, "i": 51}, {"text": "de", "x": 673, "y": 375, "w": 36, "h": 30, "conf": 97.0, "block": 1, "par": 1, "line": 4, "i": 52}, {"text": "façon", "x": 722, "y": 374, "w": 80, "h": 38, "conf": 96.0, "block": 1, "par": 1, "line": 4, "i": 53}, {"text": "explicite", "x": 817, "y": 375, "w": 120, "h": 38, "conf": 96.0, "block": 1, "par": 1, "line": 4, "i": 54}, {"text": "à", "x": 951, "y": 377, "w": 15, "h": 28, "conf": 97.0, "block": 1, "par": 1, "line": 4, "i": 55}, {"text": "certains", "x": 980, "y": 378, "w": 112, "h": 27, "conf": 95.0, "block": 1, "par": 1, "line": 4, "i": 56}, {"text": "chapitres", "x": 1105, "y": 375, "w": 132, "h": 38, "conf": 96.0, "block": 1, "par": 1, "line": 4, "i": 57}, {"text": "de", "x": 1250, "y": 375, "w": 35, "h": 30, "conf": 96.0, "block": 1, "par": 1, "line": 4, "i": 58}, {"text": "grammaire", "x": 1299, "y": 378, "w": 158, "h": 35, "conf": 96.0, "block": 1, "par": 1, "line": 4, "i": 59}, {"text": "(passé", "x": 1471, "y": 376, "w": 91, "h": 37, "conf": 93.0, "block": 1, "par": 1, "line": 4, "i": 60}, {"text": "composé/", "x": 1575, "y": 377, "w": 146, "h": 36, "conf": 92.0, "block": 1, "par": 1, "line": 4, "i": 61}, {"text": "imparfait,", "x": 149, "y": 418, "w": 139, "h": 38, "conf": 96.0, "block": 1, "par": 1, "line": 5, "i": 62}, {"text": "relatif,", "x": 301, "y": 418, "w": 90, "h": 33, "conf": 96.0, "block": 1, "par": 1, "line": 5, "i": 63}, {"text": "conditionnel,", "x": 403, "y": 418, "w": 189, "h": 33, "conf": 93.0, "block": 1, "par": 1, "line": 5, "i": 64}, {"text": "subjonctif,", "x": 605, "y": 418, "w": 151, "h": 37, "conf": 91.0, "block": 1, "par": 1, "line": 5, "i": 65}, {"text": "relations", "x": 770, "y": 418, "w": 122, "h": 29, "conf": 96.0, "block": 1, "par": 1, "line": 5, "i": 66}, {"text": "logiques)", "x": 904, "y": 418, "w": 131, "h": 38, "conf": 96.0, "block": 1, "par": 1, "line": 5, "i": 67}, {"text": "et", "x": 1047, "y": 421, "w": 29, "h": 26, "conf": 96.0, "block": 1, "par": 1, "line": 5, "i": 68}, {"text": "peuvent", "x": 1086, "y": 421, "w": 120, "h": 35, "conf": 93.0, "block": 1, "par": 1, "line": 5, "i": 69}, {"text": "s'insérer", "x": 1216, "y": 420, "w": 121, "h": 27, "conf": 91.0, "block": 1, "par": 1, "line": 5, "i": 70}, {"text": "en", "x": 1346, "y": 427, "w": 34, "h": 20, "conf": 96.0, "block": 1, "par": 1, "line": 5, "i": 71}, {"text": "cours", "x": 1392, "y": 427, "w": 78, "h": 20, "conf": 96.0, "block": 1, "par": 1, "line": 5, "i": 72}, {"text": "d'apprentissage.", "x": 1480, "y": 418, "w": 239, "h": 38, "conf": 95.0, "block": 1, "par": 1, "line": 5, "i": 73}, {"text": "Les", "x": 180, "y": 484, "w": 44, "h": 27, "conf": 96.0, "block": 2, "par": 1, "line": 1, "i": 74}, {"text": "corrigés", "x": 234, "y": 483, "w": 118, "h": 36, "conf": 96.0, "block": 2, "par": 1, "line": 1, "i": 75}, {"text": "des", "x": 363, "y": 482, "w": 48, "h": 29, "conf": 96.0, "block": 2, "par": 1, "line": 1, "i": 76}, {"text": "exercices", "x": 421, "y": 484, "w": 132, "h": 27, "conf": 96.0, "block": 2, "par": 1, "line": 1, "i": 77}, {"text": "et", "x": 563, "y": 484, "w": 28, "h": 27, "conf": 96.0, "block": 2, "par": 1, "line": 1, "i": 78}, {"text": "des", "x": 600, "y": 482, "w": 49, "h": 29, "conf": 96.0, "block": 2, "par": 1, "line": 1, "i": 79}, {"text": "activités", "x": 659, "y": 483, "w": 117, "h": 28, "conf": 93.0, "block": 2, "par": 1, "line": 1, "i": 80}, {"text": "communicatives,", "x": 787, "y": 484, "w": 245, "h": 31, "conf": 90.0, "block": 2, "par": 1, "line": 1, "i": 81}, {"text": "ainsi", "x": 1043, "y": 484, "w": 63, "h": 27, "conf": 96.0, "block": 2, "par": 1, "line": 1, "i": 82}, {"text": "que", "x": 1117, "y": 490, "w": 55, "h": 29, "conf": 96.0, "block": 2, "par": 1, "line": 1, "i": 83}, {"text": "des", "x": 1182, "y": 482, "w": 49, "h": 29, "conf": 97.0, "block": 2, "par": 1, "line": 1, "i": 84}, {"text": "suggestions", "x": 1241, "y": 484, "w": 172, "h": 35, "conf": 96.0, "block": 2, "par": 1, "line": 1, "i": 85}, {"text": "pour", "x": 1424, "y": 490, "w": 68, "h": 29, "conf": 95.0, "block": 2, "par": 1, "line": 1, "i": 86}, {"text": "les", "x": 1502, "y": 482, "w": 36, "h": 29, "conf": 96.0, "block": 2, "par": 1, "line": 1, "i": 87}, {"text": "productions", "x": 1549, "y": 482, "w": 173, "h": 37, "conf": 96.0, "block": 2, "par": 1, "line": 1, "i": 88}, {"text": "libres", "x": 149, "y": 525, "w": 75, "h": 29, "conf": 96.0, "block": 2, "par": 1, "line": 2, "i": 89}, {"text": "se", "x": 235, "y": 534, "w": 29, "h": 20, "conf": 96.0, "block": 2, "par": 1, "line": 2, "i": 90}, {"text": "trouvent", "x": 275, "y": 528, "w": 127, "h": 26, "conf": 96.0, "block": 2, "par": 1, "line": 2, "i": 91}, {"text": "dans", "x": 411, "y": 525, "w": 69, "h": 29, "conf": 96.0, "block": 2, "par": 1, "line": 2, "i": 92}, {"text": "un", "x": 492, "y": 534, "w": 34, "h": 20, "conf": 96.0, "block": 2, "par": 1, "line": 2, "i": 93}, {"text": "livret", "x": 540, "y": 525, "w": 72, "h": 29, "conf": 96.0, "block": 2, "par": 1, "line": 2, "i": 94}, {"text": "séparé.", "x": 621, "y": 527, "w": 103, "h": 36, "conf": 96.0, "block": 2, "par": 1, "line": 2, "i": 95}, {"text": "NOUVEAU", "x": 150, "y": 653, "w": 163, "h": 27, "conf": 92.0, "block": 3, "par": 1, "line": 1, "i": 96}, {"text": "!", "x": 314, "y": 647, "w": 16, "h": 46, "conf": 92.0, "block": 3, "par": 1, "line": 1, "i": 97}, {"text": "Pour", "x": 348, "y": 654, "w": 68, "h": 26, "conf": 96.0, "block": 3, "par": 1, "line": 1, "i": 98}, {"text": "s'entraîner", "x": 425, "y": 653, "w": 160, "h": 27, "conf": 80.0, "block": 3, "par": 1, "line": 1, "i": 99}, {"text": "et", "x": 595, "y": 653, "w": 28, "h": 27, "conf": 93.0, "block": 3, "par": 1, "line": 1, "i": 100}, {"text": "s'évaluer", "x": 633, "y": 651, "w": 135, "h": 29, "conf": 88.0, "block": 3, "par": 1, "line": 1, "i": 101}, {"text": "en", "x": 777, "y": 660, "w": 34, "h": 20, "conf": 96.0, "block": 3, "par": 1, "line": 1, "i": 102}, {"text": "ligne", "x": 825, "y": 651, "w": 73, "h": 37, "conf": 96.0, "block": 3, "par": 1, "line": 1, "i": 103}, {"text": "Dans", "x": 150, "y": 717, "w": 72, "h": 26, "conf": 96.0, "block": 4, "par": 1, "line": 1, "i": 104}, {"text": "cette", "x": 231, "y": 717, "w": 72, "h": 26, "conf": 96.0, "block": 4, "par": 1, "line": 1, "i": 105}, {"text": "quatrième", "x": 312, "y": 716, "w": 149, "h": 36, "conf": 95.0, "block": 4, "par": 1, "line": 1, "i": 106}, {"text": "édition,", "x": 471, "y": 714, "w": 108, "h": 33, "conf": 96.0, "block": 4, "par": 1, "line": 1, "i": 107}, {"text": "des", "x": 590, "y": 714, "w": 50, "h": 29, "conf": 96.0, "block": 4, "par": 1, "line": 1, "i": 108}, {"text": "exercices", "x": 650, "y": 717, "w": 134, "h": 26, "conf": 96.0, "block": 4, "par": 1, "line": 1, "i": 109}, {"text": "complémentaires", "x": 794, "y": 714, "w": 256, "h": 37, "conf": 93.0, "block": 4, "par": 1, "line": 1, "i": 110}, {"text": "auto-correctifs", "x": 1059, "y": 714, "w": 218, "h": 29, "conf": 92.0, "block": 4, "par": 1, "line": 1, "i": 111}, {"text": "sont", "x": 1287, "y": 717, "w": 63, "h": 26, "conf": 96.0, "block": 4, "par": 1, "line": 1, "i": 112}, {"text": "disponibles", "x": 1359, "y": 714, "w": 162, "h": 38, "conf": 96.0, "block": 4, "par": 1, "line": 1, "i": 113}, {"text": "en", "x": 1530, "y": 723, "w": 34, "h": 20, "conf": 95.0, "block": 4, "par": 1, "line": 1, "i": 114}, {"text": "ligne", "x": 1575, "y": 714, "w": 69, "h": 37, "conf": 95.0, "block": 4, "par": 1, "line": 1, "i": 115}, {"text": "pour", "x": 1655, "y": 723, "w": 68, "h": 29, "conf": 96.0, "block": 4, "par": 1, "line": 1, "i": 116}, {"text": "suivre", "x": 149, "y": 760, "w": 84, "h": 27, "conf": 96.0, "block": 4, "par": 1, "line": 2, "i": 117}, {"text": "ses", "x": 244, "y": 766, "w": 43, "h": 21, "conf": 96.0, "block": 4, "par": 1, "line": 2, "i": 118}, {"text": "progrès", "x": 299, "y": 759, "w": 110, "h": 36, "conf": 96.0, "block": 4, "par": 1, "line": 2, "i": 119}, {"text": "jour", "x": 418, "y": 760, "w": 60, "h": 35, "conf": 95.0, "block": 4, "par": 1, "line": 2, "i": 120}, {"text": "après", "x": 487, "y": 759, "w": 78, "h": 36, "conf": 96.0, "block": 4, "par": 1, "line": 2, "i": 121}, {"text": "jour", "x": 574, "y": 760, "w": 59, "h": 35, "conf": 93.0, "block": 4, "par": 1, "line": 2, "i": 122}, {"text": ":", "x": 645, "y": 767, "w": 4, "h": 19, "conf": 93.0, "block": 4, "par": 1, "line": 2, "i": 123}, {"text": "-", "x": 148, "y": 817, "w": 17, "h": 4, "conf": 58.0, "block": 4, "par": 2, "line": 1, "i": 124}, {"text": "pour", "x": 177, "y": 809, "w": 68, "h": 30, "conf": 96.0, "block": 4, "par": 2, "line": 1, "i": 125}, {"text": "s'entraîner,", "x": 255, "y": 802, "w": 163, "h": 32, "conf": 96.0, "block": 4, "par": 2, "line": 1, "i": 126}, {"text": "280", "x": 432, "y": 803, "w": 56, "h": 27, "conf": 96.0, "block": 4, "par": 2, "line": 1, "i": 127}, {"text": "exercices", "x": 499, "y": 803, "w": 132, "h": 27, "conf": 96.0, "block": 4, "par": 2, "line": 1, "i": 128}, {"text": "audio", "x": 643, "y": 801, "w": 81, "h": 29, "conf": 96.0, "block": 4, "par": 2, "line": 1, "i": 129}, {"text": "qui", "x": 735, "y": 803, "w": 45, "h": 36, "conf": 96.0, "block": 4, "par": 2, "line": 1, "i": 130}, {"text": "suivent", "x": 792, "y": 803, "w": 106, "h": 27, "conf": 96.0, "block": 4, "par": 2, "line": 1, "i": 131}, {"text": "les", "x": 909, "y": 801, "w": 37, "h": 29, "conf": 96.0, "block": 4, "par": 2, "line": 1, "i": 132}, {"text": "points", "x": 959, "y": 803, "w": 87, "h": 36, "conf": 96.0, "block": 4, "par": 2, "line": 1, "i": 133}, {"text": "de", "x": 1058, "y": 801, "w": 35, "h": 29, "conf": 96.0, "block": 4, "par": 2, "line": 1, "i": 134}, {"text": "grammaire", "x": 1105, "y": 803, "w": 158, "h": 35, "conf": 96.0, "block": 4, "par": 2, "line": 1, "i": 135}, {"text": "abordés", "x": 1275, "y": 801, "w": 116, "h": 29, "conf": 96.0, "block": 4, "par": 2, "line": 1, "i": 136}, {"text": "aux", "x": 1403, "y": 809, "w": 51, "h": 21, "conf": 96.0, "block": 4, "par": 2, "line": 1, "i": 137}, {"text": "niveaux", "x": 1468, "y": 803, "w": 112, "h": 27, "conf": 96.0, "block": 4, "par": 2, "line": 1, "i": 138}, {"text": "A2", "x": 1592, "y": 803, "w": 40, "h": 26, "conf": 96.0, "block": 4, "par": 2, "line": 1, "i": 139}, {"text": "et", "x": 1645, "y": 803, "w": 29, "h": 27, "conf": 93.0, "block": 4, "par": 2, "line": 1, "i": 140}, {"text": "B1", "x": 1687, "y": 803, "w": 29, "h": 26, "conf": 92.0, "block": 4, "par": 2, "line": 1, "i": 141}, {"text": "du", "x": 149, "y": 845, "w": 35, "h": 29, "conf": 93.0, "block": 4, "par": 2, "line": 2, "i": 142}, {"text": "—", "x": 147, "y": 904, "w": 18, "h": 4, "conf": 81.0, "block": 4, "par": 3, "line": 1, "i": 143}, {"text": "pour", "x": 177, "y": 897, "w": 67, "h": 29, "conf": 93.0, "block": 4, "par": 3, "line": 1, "i": 144}, {"text": "s'évaluer,", "x": 254, "y": 888, "w": 138, "h": 33, "conf": 85.0, "block": 4, "par": 3, "line": 1, "i": 145}, {"text": "136", "x": 406, "y": 890, "w": 55, "h": 27, "conf": 96.0, "block": 4, "par": 3, "line": 1, "i": 146}, {"text": "tests", "x": 472, "y": 890, "w": 66, "h": 27, "conf": 96.0, "block": 4, "par": 3, "line": 1, "i": 147}, {"text": "regroupés", "x": 550, "y": 890, "w": 146, "h": 35, "conf": 96.0, "block": 4, "par": 3, "line": 1, "i": 148}, {"text": "par", "x": 708, "y": 897, "w": 46, "h": 28, "conf": 96.0, "block": 4, "par": 3, "line": 1, "i": 149}, {"text": "chapitre", "x": 764, "y": 888, "w": 118, "h": 38, "conf": 93.0, "block": 4, "par": 3, "line": 1, "i": 150}, {"text": "grammatical", "x": 893, "y": 888, "w": 181, "h": 37, "conf": 91.0, "block": 4, "par": 3, "line": 1, "i": 151}, {"text": "(l'article,", "x": 1086, "y": 888, "w": 123, "h": 33, "conf": 88.0, "block": 4, "par": 3, "line": 1, "i": 152}, {"text": "le", "x": 1223, "y": 888, "w": 23, "h": 29, "conf": 96.0, "block": 4, "par": 3, "line": 1, "i": 153}, {"text": "présent,", "x": 1258, "y": 890, "w": 114, "h": 35, "conf": 96.0, "block": 4, "par": 3, "line": 1, "i": 154}, {"text": "etc.)", "x": 1385, "y": 889, "w": 64, "h": 31, "conf": 93.0, "block": 4, "par": 3, "line": 1, "i": 155}, {"text": ";", "x": 1463, "y": 897, "w": 4, "h": 24, "conf": 93.0, "block": 4, "par": 3, "line": 1, "i": 156}, {"text": "-", "x": 147, "y": 947, "w": 18, "h": 4, "conf": 47.0, "block": 4, "par": 4, "line": 1, "i": 157}, {"text": "un", "x": 177, "y": 940, "w": 34, "h": 21, "conf": 96.0, "block": 4, "par": 4, "line": 1, "i": 158}, {"text": "test", "x": 224, "y": 934, "w": 53, "h": 27, "conf": 95.0, "block": 4, "par": 4, "line": 1, "i": 159}, {"text": "de", "x": 287, "y": 931, "w": 35, "h": 30, "conf": 95.0, "block": 4, "par": 4, "line": 1, "i": 160}, {"text": "placement", "x": 335, "y": 931, "w": 152, "h": 38, "conf": 93.0, "block": 4, "par": 4, "line": 1, "i": 161}, {"text": ";", "x": 499, "y": 941, "w": 4, "h": 23, "conf": 93.0, "block": 4, "par": 4, "line": 1, "i": 162}, {"text": "-", "x": 147, "y": 991, "w": 18, "h": 4, "conf": 44.0, "block": 4, "par": 5, "line": 1, "i": 163}, {"text": "un", "x": 177, "y": 984, "w": 34, "h": 21, "conf": 96.0, "block": 4, "par": 5, "line": 1, "i": 164}, {"text": "bilan.", "x": 225, "y": 975, "w": 75, "h": 29, "conf": 96.0, "block": 4, "par": 5, "line": 1, "i": 165}, {"text": "Dans", "x": 150, "y": 1021, "w": 72, "h": 26, "conf": 95.0, "block": 5, "par": 1, "line": 1, "i": 166}, {"text": "le", "x": 234, "y": 1018, "w": 22, "h": 29, "conf": 96.0, "block": 5, "par": 1, "line": 1, "i": 167}, {"text": "livre,", "x": 269, "y": 1018, "w": 66, "h": 33, "conf": 96.0, "block": 5, "par": 1, "line": 1, "i": 168}, {"text": "des", "x": 348, "y": 1018, "w": 49, "h": 29, "conf": 96.0, "block": 5, "par": 1, "line": 1, "i": 169}, {"text": "renvois", "x": 409, "y": 1021, "w": 104, "h": 26, "conf": 96.0, "block": 5, "par": 1, "line": 1, "i": 170}, {"text": "indiquent", "x": 525, "y": 1019, "w": 139, "h": 37, "conf": 96.0, "block": 5, "par": 1, "line": 1, "i": 171}, {"text": "les", "x": 675, "y": 1018, "w": 36, "h": 29, "conf": 96.0, "block": 5, "par": 1, "line": 1, "i": 172}, {"text": "exercices", "x": 721, "y": 1021, "w": 132, "h": 26, "conf": 96.0, "block": 5, "par": 1, "line": 1, "i": 173}, {"text": "complémentaires", "x": 864, "y": 1019, "w": 251, "h": 37, "conf": 96.0, "block": 5, "par": 1, "line": 1, "i": 174}, {"text": "en", "x": 1126, "y": 1027, "w": 34, "h": 20, "conf": 96.0, "block": 5, "par": 1, "line": 1, "i": 175}, {"text": "ligne", "x": 1173, "y": 1019, "w": 69, "h": 37, "conf": 93.0, "block": 5, "par": 1, "line": 1, "i": 176}, {"text": ":", "x": 1255, "y": 1028, "w": 4, "h": 19, "conf": 93.0, "block": 5, "par": 1, "line": 1, "i": 177}, {"text": "DESCRIPTIF", "x": 151, "y": 1199, "w": 312, "h": 36, "conf": 96.0, "block": 6, "par": 1, "line": 1, "i": 178}, {"text": "L'UNITÉ", "x": 189, "y": 1295, "w": 113, "h": 33, "conf": 91.0, "block": 7, "par": 1, "line": 1, "i": 179}, {"text": "GRAMMATICALE", "x": 315, "y": 1301, "w": 252, "h": 27, "conf": 85.0, "block": 7, "par": 1, "line": 1, "i": 180}, {"text": ":", "x": 582, "y": 1309, "w": 4, "h": 18, "conf": 91.0, "block": 7, "par": 1, "line": 1, "i": 181}, {"text": "LES", "x": 969, "y": 1303, "w": 51, "h": 29, "conf": 93.0, "block": 7, "par": 1, "line": 1, "i": 182}, {"text": "EXERCICES", "x": 1034, "y": 1303, "w": 172, "h": 29, "conf": 91.0, "block": 7, "par": 1, "line": 1, "i": 183}, {"text": ":", "x": 1221, "y": 1311, "w": 5, "h": 20, "conf": 91.0, "block": 7, "par": 1, "line": 1, "i": 184}, {"text": "Une", "x": 1123, "y": 1395, "w": 56, "h": 25, "conf": 96.0, "block": 9, "par": 1, "line": 1, "i": 185}, {"text": "ou", "x": 1190, "y": 1400, "w": 34, "h": 20, "conf": 96.0, "block": 9, "par": 1, "line": 1, "i": 186}, {"text": "trois", "x": 1237, "y": 1395, "w": 63, "h": 25, "conf": 96.0, "block": 9, "par": 1, "line": 1, "i": 187}, {"text": "pages", "x": 1312, "y": 1400, "w": 82, "h": 28, "conf": 96.0, "block": 9, "par": 1, "line": 1, "i": 188}, {"text": "d'exercices", "x": 1406, "y": 1392, "w": 156, "h": 28, "conf": 88.0, "block": 9, "par": 1, "line": 1, "i": 189}, {"text": ":", "x": 1574, "y": 1401, "w": 5, "h": 18, "conf": 93.0, "block": 9, "par": 1, "line": 1, "i": 190}, {"text": "selon", "x": 1095, "y": 1440, "w": 71, "h": 28, "conf": 96.0, "block": 10, "par": 1, "line": 1, "i": 191}, {"text": "l'importance", "x": 1179, "y": 1440, "w": 175, "h": 36, "conf": 89.0, "block": 10, "par": 1, "line": 1, "i": 192}, {"text": "des", "x": 1365, "y": 1440, "w": 46, "h": 28, "conf": 96.0, "block": 10, "par": 1, "line": 1, "i": 193}, {"text": "problèmes.", "x": 1423, "y": 1440, "w": 151, "h": 36, "conf": 96.0, "block": 10, "par": 1, "line": 1, "i": 194}, {"text": "le", "x": 407, "y": 1463, "w": 24, "h": 29, "conf": 94.0, "block": 11, "par": 1, "line": 1, "i": 195}, {"text": "point", "x": 442, "y": 1465, "w": 74, "h": 34, "conf": 94.0, "block": 11, "par": 1, "line": 1, "i": 196}, {"text": "principal.", "x": 527, "y": 1463, "w": 131, "h": 36, "conf": 96.0, "block": 11, "par": 1, "line": 1, "i": 197}, {"text": "+", "x": 1093, "y": 1507, "w": 12, "h": 13, "conf": 46.0, "block": 13, "par": 1, "line": 1, "i": 198}, {"text": "Des", "x": 1121, "y": 1501, "w": 51, "h": 26, "conf": 96.0, "block": 13, "par": 1, "line": 1, "i": 199}, {"text": "exercices", "x": 1184, "y": 1501, "w": 128, "h": 26, "conf": 96.0, "block": 13, "par": 1, "line": 1, "i": 200}, {"text": "variés", "x": 1324, "y": 1500, "w": 82, "h": 27, "conf": 93.0, "block": 13, "par": 1, "line": 1, "i": 201}, {"text": ":", "x": 1419, "y": 1508, "w": 5, "h": 18, "conf": 92.0, "block": 13, "par": 1, "line": 1, "i": 202}, {"text": "découverte,", "x": 1095, "y": 1547, "w": 164, "h": 32, "conf": 93.0, "block": 13, "par": 1, "line": 2, "i": 203}, {"text": "réemploi,", "x": 1273, "y": 1547, "w": 127, "h": 36, "conf": 91.0, "block": 13, "par": 1, "line": 2, "i": 204}, {"text": "mécanisation,", "x": 1415, "y": 1549, "w": 191, "h": 30, "conf": 91.0, "block": 13, "par": 1, "line": 2, "i": 205}, {"text": "activités", "x": 1095, "y": 1597, "w": 113, "h": 27, "conf": 96.0, "block": 13, "par": 1, "line": 3, "i": 206}, {"text": "libres,", "x": 1219, "y": 1596, "w": 79, "h": 32, "conf": 96.0, "block": 13, "par": 1, "line": 3, "i": 207}, {"text": "textes,", "x": 1311, "y": 1599, "w": 91, "h": 29, "conf": 96.0, "block": 13, "par": 1, "line": 3, "i": 208}, {"text": "etc.", "x": 1415, "y": 1599, "w": 48, "h": 25, "conf": 96.0, "block": 13, "par": 1, "line": 3, "i": 209}, {"text": "+", "x": 317, "y": 1557, "w": 12, "h": 13, "conf": 69.0, "block": 14, "par": 1, "line": 1, "i": 210}, {"text": "Des", "x": 344, "y": 1551, "w": 52, "h": 26, "conf": 96.0, "block": 14, "par": 1, "line": 1, "i": 211}, {"text": "explications", "x": 407, "y": 1549, "w": 171, "h": 35, "conf": 96.0, "block": 14, "par": 1, "line": 1, "i": 212}, {"text": "simples", "x": 589, "y": 1549, "w": 109, "h": 35, "conf": 96.0, "block": 14, "par": 1, "line": 1, "i": 213}, {"text": "avec", "x": 316, "y": 1605, "w": 63, "h": 20, "conf": 96.0, "block": 14, "par": 1, "line": 2, "i": 214}, {"text": "des", "x": 401, "y": 1597, "w": 46, "h": 28, "conf": 96.0, "block": 14, "par": 1, "line": 2, "i": 215}, {"text": "exemples", "x": 470, "y": 1597, "w": 130, "h": 36, "conf": 96.0, "block": 14, "par": 1, "line": 2, "i": 216}, {"text": "clairs", "x": 623, "y": 1597, "w": 68, "h": 28, "conf": 96.0, "block": 14, "par": 1, "line": 2, "i": 217}, {"text": "et", "x": 713, "y": 1599, "w": 27, "h": 26, "conf": 96.0, "block": 14, "par": 1, "line": 2, "i": 218}, {"text": "nombreux.", "x": 763, "y": 1597, "w": 149, "h": 28, "conf": 95.0, "block": 14, "par": 1, "line": 2, "i": 219}, {"text": "+", "x": 317, "y": 1663, "w": 12, "h": 13, "conf": 58.0, "block": 15, "par": 1, "line": 1, "i": 220}, {"text": "Une", "x": 343, "y": 1658, "w": 56, "h": 25, "conf": 95.0, "block": 15, "par": 1, "line": 1, "i": 221}, {"text": "démarche", "x": 411, "y": 1655, "w": 138, "h": 28, "conf": 95.0, "block": 15, "par": 1, "line": 1, "i": 222}, {"text": "progressive", "x": 561, "y": 1658, "w": 163, "h": 33, "conf": 96.0, "block": 15, "par": 1, "line": 1, "i": 223}, {"text": "C1)", "x": 962, "y": 1634, "w": 114, "h": 65, "conf": 43.0, "block": 15, "par": 1, "line": 1, "i": 224}, {"text": "+", "x": 1093, "y": 1663, "w": 12, "h": 13, "conf": 67.0, "block": 15, "par": 1, "line": 1, "i": 225}, {"text": "Des", "x": 1121, "y": 1657, "w": 51, "h": 26, "conf": 96.0, "block": 15, "par": 1, "line": 1, "i": 226}, {"text": "exercices", "x": 1184, "y": 1657, "w": 128, "h": 26, "conf": 93.0, "block": 15, "par": 1, "line": 1, "i": 227}, {"text": "récapitulatifs", "x": 1325, "y": 1654, "w": 184, "h": 36, "conf": 91.0, "block": 15, "par": 1, "line": 1, "i": 228}, {"text": ":", "x": 1522, "y": 1664, "w": 5, "h": 18, "conf": 93.0, "block": 15, "par": 1, "line": 1, "i": 229}, {"text": "+", "x": 314, "y": 1723, "w": 12, "h": 12, "conf": 64.0, "block": 15, "par": 1, "line": 2, "i": 230}, {"text": "Des", "x": 341, "y": 1717, "w": 51, "h": 25, "conf": 94.0, "block": 15, "par": 1, "line": 2, "i": 231}, {"text": "mises", "x": 405, "y": 1717, "w": 79, "h": 25, "conf": 96.0, "block": 15, "par": 1, "line": 2, "i": 232}, {"text": "en", "x": 497, "y": 1722, "w": 32, "h": 20, "conf": 96.0, "block": 15, "par": 1, "line": 2, "i": 233}, {"text": "garde", "x": 542, "y": 1714, "w": 79, "h": 36, "conf": 93.0, "block": 15, "par": 1, "line": 2, "i": 234}, {"text": ":", "x": 633, "y": 1724, "w": 5, "h": 17, "conf": 93.0, "block": 15, "par": 1, "line": 2, "i": 235}, {"text": "contenant", "x": 1095, "y": 1706, "w": 142, "h": 26, "conf": 96.0, "block": 15, "par": 1, "line": 2, "i": 236}, {"text": "des", "x": 1248, "y": 1704, "w": 46, "h": 28, "conf": 96.0, "block": 15, "par": 1, "line": 2, "i": 237}, {"text": "points", "x": 1307, "y": 1706, "w": 84, "h": 33, "conf": 95.0, "block": 15, "par": 1, "line": 2, "i": 238}, {"text": "déjà", "x": 1402, "y": 1703, "w": 57, "h": 36, "conf": 96.0, "block": 15, "par": 1, "line": 2, "i": 239}, {"text": "vus.", "x": 1471, "y": 1711, "w": 53, "h": 21, "conf": 96.0, "block": 15, "par": 1, "line": 2, "i": 240}, {"text": "difficultés", "x": 315, "y": 1763, "w": 135, "h": 28, "conf": 96.0, "block": 16, "par": 1, "line": 1, "i": 241}, {"text": "particulières", "x": 462, "y": 1763, "w": 166, "h": 36, "conf": 96.0, "block": 16, "par": 1, "line": 1, "i": 242}, {"text": "et", "x": 639, "y": 1765, "w": 28, "h": 26, "conf": 97.0, "block": 16, "par": 1, "line": 1, "i": 243}, {"text": "+", "x": 1093, "y": 1771, "w": 12, "h": 13, "conf": 68.0, "block": 16, "par": 1, "line": 1, "i": 244}, {"text": "Des", "x": 1121, "y": 1765, "w": 51, "h": 25, "conf": 96.0, "block": 16, "par": 1, "line": 1, "i": 245}, {"text": "productions", "x": 1185, "y": 1763, "w": 167, "h": 35, "conf": 96.0, "block": 16, "par": 1, "line": 1, "i": 246}, {"text": "libres", "x": 1366, "y": 1763, "w": 75, "h": 27, "conf": 96.0, "block": 16, "par": 1, "line": 1, "i": 247}, {"text": "ou", "x": 1453, "y": 1771, "w": 35, "h": 20, "conf": 97.0, "block": 16, "par": 1, "line": 1, "i": 248}, {"text": "guidées", "x": 1500, "y": 1763, "w": 106, "h": 35, "conf": 96.0, "block": 16, "par": 1, "line": 1, "i": 249}, {"text": "interférences", "x": 316, "y": 1811, "w": 180, "h": 29, "conf": 96.0, "block": 16, "par": 1, "line": 2, "i": 250}, {"text": "fréquentes.", "x": 507, "y": 1811, "w": 156, "h": 37, "conf": 95.0, "block": 16, "par": 1, "line": 2, "i": 251}, {"text": "et", "x": 1092, "y": 1813, "w": 27, "h": 26, "conf": 96.0, "block": 16, "par": 1, "line": 2, "i": 252}, {"text": "des", "x": 1129, "y": 1811, "w": 47, "h": 28, "conf": 95.0, "block": 16, "par": 1, "line": 2, "i": 253}, {"text": "suggestions", "x": 1187, "y": 1813, "w": 164, "h": 33, "conf": 96.0, "block": 16, "par": 1, "line": 2, "i": 254}, {"text": "de", "x": 1363, "y": 1811, "w": 33, "h": 28, "conf": 97.0, "block": 16, "par": 1, "line": 2, "i": 255}, {"text": "recherches.", "x": 1409, "y": 1811, "w": 154, "h": 28, "conf": 96.0, "block": 16, "par": 1, "line": 2, "i": 256}, {"text": "+", "x": 314, "y": 1879, "w": 12, "h": 12, "conf": 73.0, "block": 16, "par": 2, "line": 1, "i": 257}, {"text": "Des", "x": 341, "y": 1873, "w": 51, "h": 25, "conf": 96.0, "block": 16, "par": 2, "line": 1, "i": 258}, {"text": "remarques", "x": 405, "y": 1879, "w": 148, "h": 27, "conf": 93.0, "block": 16, "par": 2, "line": 1, "i": 259}, {"text": "phonétiques", "x": 565, "y": 1870, "w": 176, "h": 36, "conf": 91.0, "block": 16, "par": 2, "line": 1, "i": 260}, {"text": ":", "x": 753, "y": 1880, "w": 5, "h": 18, "conf": 93.0, "block": 16, "par": 2, "line": 1, "i": 261}, {"text": "+", "x": 1096, "y": 1878, "w": 12, "h": 13, "conf": 63.0, "block": 16, "par": 2, "line": 1, "i": 262}, {"text": "Des", "x": 1123, "y": 1872, "w": 52, "h": 26, "conf": 96.0, "block": 16, "par": 2, "line": 1, "i": 263}, {"text": "bilans", "x": 1188, "y": 1870, "w": 83, "h": 28, "conf": 96.0, "block": 16, "par": 2, "line": 1, "i": 264}, {"text": "notés", "x": 1284, "y": 1871, "w": 76, "h": 27, "conf": 93.0, "block": 16, "par": 2, "line": 1, "i": 265}, {"text": ":", "x": 1373, "y": 1879, "w": 5, "h": 18, "conf": 92.0, "block": 16, "par": 2, "line": 1, "i": 266}, {"text": "liaison,", "x": 316, "y": 1919, "w": 94, "h": 32, "conf": 93.0, "block": 16, "par": 3, "line": 1, "i": 267}, {"text": "élision,", "x": 423, "y": 1919, "w": 93, "h": 31, "conf": 89.0, "block": 16, "par": 3, "line": 1, "i": 268}, {"text": "contraction,", "x": 530, "y": 1922, "w": 166, "h": 29, "conf": 95.0, "block": 16, "par": 3, "line": 1, "i": 269}, {"text": "etc.", "x": 709, "y": 1922, "w": 48, "h": 25, "conf": 96.0, "block": 16, "par": 3, "line": 1, "i": 270}, {"text": "pour", "x": 1096, "y": 1926, "w": 65, "h": 28, "conf": 96.0, "block": 16, "par": 3, "line": 1, "i": 271}, {"text": "évaluer", "x": 1171, "y": 1918, "w": 103, "h": 28, "conf": 96.0, "block": 16, "par": 3, "line": 1, "i": 272}, {"text": "les", "x": 1284, "y": 1918, "w": 35, "h": 28, "conf": 96.0, "block": 16, "par": 3, "line": 1, "i": 273}, {"text": "acquis.", "x": 1331, "y": 1921, "w": 93, "h": 33, "conf": 96.0, "block": 16, "par": 3, "line": 1, "i": 274}, {"text": "Note", "x": 149, "y": 2217, "w": 54, "h": 21, "conf": 96.0, "block": 18, "par": 1, "line": 1, "i": 275}, {"text": "sur", "x": 211, "y": 2221, "w": 35, "h": 17, "conf": 96.0, "block": 18, "par": 1, "line": 1, "i": 276}, {"text": "la", "x": 253, "y": 2215, "w": 20, "h": 23, "conf": 96.0, "block": 18, "par": 1, "line": 1, "i": 277}, {"text": "formation", "x": 280, "y": 2215, "w": 112, "h": 23, "conf": 96.0, "block": 18, "par": 1, "line": 1, "i": 278}, {"text": "de", "x": 400, "y": 2215, "w": 28, "h": 23, "conf": 93.0, "block": 18, "par": 1, "line": 1, "i": 279}, {"text": "l'imparfait", "x": 436, "y": 2215, "w": 118, "h": 29, "conf": 84.0, "block": 18, "par": 1, "line": 1, "i": 280}, {"text": "et", "x": 561, "y": 2217, "w": 22, "h": 21, "conf": 95.0, "block": 18, "par": 1, "line": 1, "i": 281}, {"text": "du", "x": 590, "y": 2215, "w": 28, "h": 23, "conf": 93.0, "block": 18, "par": 1, "line": 1, "i": 282}, {"text": "gérondif", "x": 626, "y": 2215, "w": 96, "h": 29, "conf": 90.0, "block": 18, "par": 1, "line": 1, "i": 283}, {"text": ":", "x": 731, "y": 2222, "w": 4, "h": 15, "conf": 92.0, "block": 18, "par": 1, "line": 1, "i": 284}, {"text": "Pour", "x": 745, "y": 2216, "w": 52, "h": 22, "conf": 96.0, "block": 18, "par": 1, "line": 1, "i": 285}, {"text": "les", "x": 805, "y": 2215, "w": 28, "h": 23, "conf": 96.0, "block": 18, "par": 1, "line": 1, "i": 286}, {"text": "étudiants", "x": 840, "y": 2215, "w": 104, "h": 23, "conf": 96.0, "block": 18, "par": 1, "line": 1, "i": 287}, {"text": "en", "x": 951, "y": 2221, "w": 27, "h": 17, "conf": 93.0, "block": 18, "par": 1, "line": 1, "i": 288}, {"text": "auto-apprentissage,", "x": 986, "y": 2217, "w": 223, "h": 27, "conf": 91.0, "block": 18, "par": 1, "line": 1, "i": 289}, {"text": "les", "x": 1219, "y": 2215, "w": 27, "h": 23, "conf": 96.0, "block": 18, "par": 1, "line": 1, "i": 290}, {"text": "formes", "x": 1255, "y": 2215, "w": 76, "h": 23, "conf": 96.0, "block": 18, "par": 1, "line": 1, "i": 291}, {"text": "du", "x": 1339, "y": 2215, "w": 27, "h": 23, "conf": 97.0, "block": 18, "par": 1, "line": 1, "i": 292}, {"text": "dialogue", "x": 1375, "y": 2215, "w": 96, "h": 28, "conf": 93.0, "block": 18, "par": 1, "line": 1, "i": 293}, {"text": "«", "x": 1481, "y": 2224, "w": 10, "h": 10, "conf": 92.0, "block": 18, "par": 1, "line": 1, "i": 294}, {"text": "Je", "x": 1500, "y": 2217, "w": 22, "h": 21, "conf": 93.0, "block": 18, "par": 1, "line": 1, "i": 295}, {"text": "»/«", "x": 1532, "y": 2217, "w": 36, "h": 20, "conf": 92.0, "block": 18, "par": 1, "line": 1, "i": 296}, {"text": "Vous", "x": 1577, "y": 2216, "w": 57, "h": 22, "conf": 93.0, "block": 18, "par": 1, "line": 1, "i": 297}, {"text": "»", "x": 1644, "y": 2224, "w": 10, "h": 10, "conf": 93.0, "block": 18, "par": 1, "line": 1, "i": 298}, {"text": "étant", "x": 1664, "y": 2217, "w": 58, "h": 21, "conf": 96.0, "block": 18, "par": 1, "line": 1, "i": 299}, {"text": "acquises", "x": 148, "y": 2251, "w": 93, "h": 27, "conf": 96.0, "block": 18, "par": 1, "line": 2, "i": 300}, {"text": "en", "x": 250, "y": 2255, "w": 26, "h": 17, "conf": 96.0, "block": 18, "par": 1, "line": 2, "i": 301}, {"text": "priorité,", "x": 287, "y": 2251, "w": 85, "h": 27, "conf": 96.0, "block": 18, "par": 1, "line": 2, "i": 302}, {"text": "il", "x": 383, "y": 2250, "w": 10, "h": 21, "conf": 96.0, "block": 18, "par": 1, "line": 2, "i": 303}, {"text": "est", "x": 402, "y": 2252, "w": 33, "h": 20, "conf": 96.0, "block": 18, "par": 1, "line": 2, "i": 304}, {"text": "plus", "x": 444, "y": 2250, "w": 44, "h": 28, "conf": 96.0, "block": 18, "par": 1, "line": 2, "i": 305}, {"text": "facile", "x": 497, "y": 2249, "w": 57, "h": 23, "conf": 96.0, "block": 18, "par": 1, "line": 2, "i": 306}, {"text": "de", "x": 563, "y": 2250, "w": 28, "h": 22, "conf": 96.0, "block": 18, "par": 1, "line": 2, "i": 307}, {"text": "construire", "x": 600, "y": 2251, "w": 110, "h": 21, "conf": 93.0, "block": 18, "par": 1, "line": 2, "i": 308}, {"text": "l'imparfait", "x": 721, "y": 2249, "w": 113, "h": 29, "conf": 90.0, "block": 18, "par": 1, "line": 2, "i": 309}, {"text": "à", "x": 843, "y": 2251, "w": 13, "h": 21, "conf": 96.0, "block": 18, "par": 1, "line": 2, "i": 310}, {"text": "partir", "x": 865, "y": 2251, "w": 59, "h": 27, "conf": 96.0, "block": 18, "par": 1, "line": 2, "i": 311}, {"text": "du", "x": 932, "y": 2250, "w": 28, "h": 22, "conf": 91.0, "block": 18, "par": 1, "line": 2, "i": 312}, {"text": "«", "x": 972, "y": 2258, "w": 10, "h": 11, "conf": 91.0, "block": 18, "par": 1, "line": 2, "i": 313}, {"text": "Vous", "x": 993, "y": 2251, "w": 57, "h": 21, "conf": 93.0, "block": 18, "par": 1, "line": 2, "i": 314}, {"text": "»", "x": 1061, "y": 2259, "w": 9, "h": 10, "conf": 92.0, "block": 18, "par": 1, "line": 2, "i": 315}, {"text": ":", "x": 1083, "y": 2257, "w": 3, "h": 15, "conf": 92.0, "block": 18, "par": 1, "line": 2, "i": 316}, {"text": "Vous", "x": 1099, "y": 2251, "w": 54, "h": 21, "conf": 96.0, "block": 18, "par": 1, "line": 2, "i": 317}, {"text": "prenez", "x": 1161, "y": 2256, "w": 80, "h": 21, "conf": 96.0, "block": 18, "par": 1, "line": 2, "i": 318}, {"text": ">", "x": 1250, "y": 2245, "w": 14, "h": 37, "conf": 60.0, "block": 18, "par": 1, "line": 2, "i": 319}, {"text": "Je", "x": 1277, "y": 2251, "w": 23, "h": 21, "conf": 93.0, "block": 18, "par": 1, "line": 2, "i": 320}, {"text": "pren-ais", "x": 1308, "y": 2251, "w": 97, "h": 26, "conf": 91.0, "block": 18, "par": 1, "line": 2, "i": 321}, {"text": "Vous", "x": 1413, "y": 2251, "w": 54, "h": 21, "conf": 96.0, "block": 18, "par": 1, "line": 2, "i": 322}, {"text": "voulez", "x": 1478, "y": 2250, "w": 76, "h": 22, "conf": 96.0, "block": 18, "par": 1, "line": 2, "i": 323}, {"text": ">", "x": 1574, "y": 2258, "w": 6, "h": 7, "conf": 72.0, "block": 18, "par": 1, "line": 2, "i": 324}, {"text": "Je", "x": 1590, "y": 2251, "w": 24, "h": 21, "conf": 93.0, "block": 18, "par": 1, "line": 2, "i": 325}, {"text": "voul-ais.", "x": 1623, "y": 2250, "w": 97, "h": 22, "conf": 91.0, "block": 18, "par": 1, "line": 2, "i": 326}, {"text": "Dans", "x": 149, "y": 2286, "w": 55, "h": 21, "conf": 91.0, "block": 18, "par": 1, "line": 3, "i": 327}, {"text": "les", "x": 213, "y": 2285, "w": 28, "h": 22, "conf": 92.0, "block": 18, "par": 1, "line": 3, "i": 328}, {"text": "classes,", "x": 249, "y": 2285, "w": 81, "h": 25, "conf": 95.0, "block": 18, "par": 1, "line": 3, "i": 329}, {"text": "où", "x": 338, "y": 2286, "w": 28, "h": 21, "conf": 95.0, "block": 18, "par": 1, "line": 3, "i": 330}, {"text": "le", "x": 377, "y": 2285, "w": 17, "h": 22, "conf": 93.0, "block": 18, "par": 1, "line": 3, "i": 331}, {"text": "«", "x": 404, "y": 2293, "w": 10, "h": 11, "conf": 92.0, "block": 18, "par": 1, "line": 3, "i": 332}, {"text": "Nous", "x": 425, "y": 2286, "w": 57, "h": 21, "conf": 93.0, "block": 18, "par": 1, "line": 3, "i": 333}, {"text": "»", "x": 492, "y": 2293, "w": 10, "h": 11, "conf": 92.0, "block": 18, "par": 1, "line": 3, "i": 334}, {"text": "est", "x": 512, "y": 2287, "w": 32, "h": 20, "conf": 96.0, "block": 18, "par": 1, "line": 3, "i": 335}, {"text": "rapidement", "x": 553, "y": 2285, "w": 127, "h": 28, "conf": 95.0, "block": 18, "par": 1, "line": 3, "i": 336}, {"text": "introduit,", "x": 689, "y": 2285, "w": 101, "h": 25, "conf": 96.0, "block": 18, "par": 1, "line": 3, "i": 337}, {"text": "on", "x": 799, "y": 2291, "w": 28, "h": 16, "conf": 96.0, "block": 18, "par": 1, "line": 3, "i": 338}, {"text": "recourt", "x": 837, "y": 2287, "w": 79, "h": 20, "conf": 96.0, "block": 18, "par": 1, "line": 3, "i": 339}, {"text": "plus", "x": 925, "y": 2285, "w": 44, "h": 28, "conf": 95.0, "block": 18, "par": 1, "line": 3, "i": 340}, {"text": "facilement", "x": 977, "y": 2284, "w": 117, "h": 23, "conf": 95.0, "block": 18, "par": 1, "line": 3, "i": 341}, {"text": "à", "x": 1101, "y": 2286, "w": 13, "h": 21, "conf": 95.0, "block": 18, "par": 1, "line": 3, "i": 342}, {"text": "la", "x": 1123, "y": 2285, "w": 17, "h": 22, "conf": 96.0, "block": 18, "par": 1, "line": 3, "i": 343}, {"text": "formation", "x": 1149, "y": 2284, "w": 109, "h": 23, "conf": 96.0, "block": 18, "par": 1, "line": 3, "i": 344}, {"text": "traditionnelle", "x": 1268, "y": 2285, "w": 147, "h": 22, "conf": 94.0, "block": 18, "par": 1, "line": 3, "i": 345}, {"text": "à", "x": 1423, "y": 2286, "w": 13, "h": 21, "conf": 94.0, "block": 18, "par": 1, "line": 3, "i": 346}, {"text": "partir", "x": 1445, "y": 2286, "w": 59, "h": 27, "conf": 96.0, "block": 18, "par": 1, "line": 3, "i": 347}, {"text": "du", "x": 1511, "y": 2285, "w": 27, "h": 22, "conf": 92.0, "block": 18, "par": 1, "line": 3, "i": 348}, {"text": "«", "x": 1549, "y": 2293, "w": 11, "h": 11, "conf": 92.0, "block": 18, "par": 1, "line": 3, "i": 349}, {"text": "Nous", "x": 1571, "y": 2286, "w": 57, "h": 21, "conf": 93.0, "block": 18, "par": 1, "line": 3, "i": 350}, {"text": "».", "x": 1637, "y": 2293, "w": 19, "h": 13, "conf": 92.0, "block": 18, "par": 1, "line": 3, "i": 351}, {"text": "C'est", "x": 1665, "y": 2285, "w": 57, "h": 22, "conf": 96.0, "block": 18, "par": 1, "line": 3, "i": 352}, {"text": "l'option", "x": 149, "y": 2319, "w": 83, "h": 29, "conf": 92.0, "block": 18, "par": 1, "line": 4, "i": 353}, {"text": "choisie", "x": 241, "y": 2319, "w": 76, "h": 23, "conf": 96.0, "block": 18, "par": 1, "line": 4, "i": 354}, {"text": "dans", "x": 325, "y": 2319, "w": 53, "h": 23, "conf": 96.0, "block": 18, "par": 1, "line": 4, "i": 355}, {"text": "cette", "x": 385, "y": 2321, "w": 55, "h": 21, "conf": 96.0, "block": 18, "par": 1, "line": 4, "i": 356}, {"text": "édition.", "x": 448, "y": 2319, "w": 83, "h": 23, "conf": 94.0, "block": 18, "par": 1, "line": 4, "i": 357}, {"text": "4", "x": 148, "y": 2450, "w": 16, "h": 28, "conf": 90.0, "block": 19, "par": 1, "line": 1, "i": 358}, {"text": "e", "x": 177, "y": 2457, "w": 14, "h": 14, "conf": 76.0, "block": 19, "par": 1, "line": 1, "i": 359}, {"text": "quatre", "x": 205, "y": 2454, "w": 89, "h": 31, "conf": 96.0, "block": 19, "par": 1, "line": 1, "i": 360}], "sentences": [{"id": 0, "text": "+ Des activités communicatives permettent, en fin d'ouvrage, de travailler la compréhension et la produc- tion orale et écrite en classe ou en auto-apprentissage.", "words": [0, 1, 2, 3, 4, 5, 6, 7, 8, 9, 10, 11, 12, 13, 14, 15, 16, 17, 18, 19, 20, 21, 22, 23]}, {"id": 1, "text": "Elles se composent de textes ou de dialogues enre- gistrés et retranscrits accompagnés de questions, d'exercices de réemploi ou de productions à partir d'un modèle.", "words": [24, 25, 26, 27, 28, 29, 30, 31, 32, 33, 34, 35, 36, 37, 38, 39, 40, 41, 42, 43, 44, 45, 46, 47, 48]}, {"id": 2, "text": "Ces documents renvoient de façon explicite à certains chapitres de grammaire (passé composé/ imparfait, relatif, conditionnel, subjonctif, relations logiques) et peuvent s'insérer en cours d'apprentissage.", "words": [49, 50, 51, 52, 53, 54, 55, 56, 57, 58, 59, 60, 61, 62, 63, 64, 65, 66, 67, 68, 69, 70, 71, 72, 73]}, {"id": 3, "text": "Les corrigés des exercices et des activités communicatives, ainsi que des suggestions pour les productions libres se trouvent dans un livret séparé.", "words": [74, 75, 76, 77, 78, 79, 80, 81, 82, 83, 84, 85, 86, 87, 88, 89, 90, 91, 92, 93, 94, 95]}, {"id": 4, "text": "NOUVEAU !", "words": [96, 97]}, {"id": 5, "text": "Pour s'entraîner et s'évaluer en ligne", "words": [98, 99, 100, 101, 102, 103]}, {"id": 6, "text": "Dans cette quatrième édition, des exercices complémentaires auto-correctifs sont disponibles en ligne pour suivre ses progrès jour après jour :", "words": [104, 105, 106, 107, 108, 109, 110, 111, 112, 113, 114, 115, 116, 117, 118, 119, 120, 121, 122, 123]}, {"id": 7, "text": "- pour s'entraîner, 280 exercices audio qui suivent les points de grammaire abordés aux niveaux A2 et B1 du", "words": [124, 125, 126, 127, 128, 129, 130, 131, 132, 133, 134, 135, 136, 137, 138, 139, 140, 141, 142]}, {"id": 8, "text": "— pour s'évaluer, 136 tests regroupés par chapitre grammatical (l'article, le présent, etc.)", "words": [143, 144, 145, 146, 147, 148, 149, 150, 151, 152, 153, 154, 155]}, {"id": 9, "text": ";", "words": [156]}, {"id": 10, "text": "- un test de placement ;", "words": [157, 158, 159, 160, 161, 162]}, {"id": 11, "text": "- un bilan.", "words": [163, 164, 165]}, {"id": 12, "text": "Dans le livre, des renvois indiquent les exercices complémentaires en ligne :", "words": [166, 167, 168, 169, 170, 171, 172, 173, 174, 175, 176, 177]}, {"id": 13, "text": "DESCRIPTIF", "words": [178]}, {"id": 14, "text": "L'UNITÉ GRAMMATICALE : LES EXERCICES :", "words": [179, 180, 181, 182, 183, 184]}, {"id": 15, "text": "Une ou trois pages d'exercices :", "words": [185, 186, 187, 188, 189, 190]}, {"id": 16, "text": "selon l'importance des problèmes.", "words": [191, 192, 193, 194]}, {"id": 17, "text": "le point principal.", "words": [195, 196, 197]}, {"id": 18, "text": "+ Des exercices variés : découverte, réemploi, mécanisation, activités libres, textes, etc.", "words": [198, 199, 200, 201, 202, 203, 204, 205, 206, 207, 208, 209]}, {"id": 19, "text": "+ Des explications simples avec des exemples clairs et nombreux.", "words": [210, 211, 212, 213, 214, 215, 216, 217, 218, 219]}, {"id": 20, "text": "+ Une démarche progressive C1) + Des exercices récapitulatifs : + Des mises en garde : contenant des points déjà vus.", "words": [220, 221, 222, 223, 224, 225, 226, 227, 228, 229, 230, 231, 232, 233, 234, 235, 236, 237, 238, 239, 240]}, {"id": 21, "text": "difficultés particulières et + Des productions libres ou guidées interférences fréquentes.", "words": [241, 242, 243, 244, 245, 246, 247, 248, 249, 250, 251]}, {"id": 22, "text": "et des suggestions de recherches.", "words": [252, 253, 254, 255, 256]}, {"id": 23, "text": "+ Des remarques phonétiques : + Des bilans notés :", "words": [257, 258, 259, 260, 261, 262, 263, 264, 265, 266]}, {"id": 24, "text": "liaison, élision, contraction, etc.", "words": [267, 268, 269, 270]}, {"id": 25, "text": "pour évaluer les acquis.", "words": [271, 272, 273, 274]}, {"id": 26, "text": "Note sur la formation de l'imparfait et du gérondif : Pour les étudiants en auto-apprentissage, les formes du dialogue « Je »/« Vous » étant acquises en priorité, il est plus facile de construire l'imparfait à partir du « Vous » : Vous prenez > Je pren-ais Vous voulez > Je voul-ais.", "words": [275, 276, 277, 278, 279, 280, 281, 282, 283, 284, 285, 286, 287, 288, 289, 290, 291, 292, 293, 294, 295, 296, 297, 298, 299, 300, 301, 302, 303, 304, 305, 306, 307, 308, 309, 310, 311, 312, 313, 314, 315, 316, 317, 318, 319, 320, 321, 322, 323, 324, 325, 326]}, {"id": 27, "text": "Dans les classes, où le « Nous » est rapidement introduit, on recourt plus facilement à la formation traditionnelle à partir du « Nous ».", "words": [327, 328, 329, 330, 331, 332, 333, 334, 335, 336, 337, 338, 339, 340, 341, 342, 343, 344, 345, 346, 347, 348, 349, 350, 351]}, {"id": 28, "text": "C'est l'option choisie dans cette édition.", "words": [352, 353, 354, 355, 356, 357]}, {"id": 29, "text": "4 e quatre", "words": [358, 359, 360]}]}